skosprovider/__init__.py
skosprovider/exceptions.py
skosprovider/jsonld.py
skosprovider/providers.py
skosprovider/registry.py
skosprovider/skos.py
skosprovider/uri.py
skosprovider/utils.py
skosprovider-1.5.1.dist-info/METADATA
skosprovider-1.5.1.dist-info/WHEEL
skosprovider-1.5.1.dist-info/licenses/LICENSE
skosprovider-1.5.1.dist-info/RECORD
