Metadata-Version: 2.4
Name: skosprovider
Version: 1.5.1
Summary: Abstraction layer for SKOS vocabularies.
Project-URL: History, https://github.com/OnroerendErfgoed/skosprovider/blob/master/HISTORY.rst
Project-URL: Tracker, https://github.com/OnroerendErfgoed/skosprovider/issues
Project-URL: Source, https://github.com/OnroerendErfgoed/skosprovider
Project-URL: Documentation, https://skosprovider.readthedocs.io/en/latest/
Author-email: Flanders Heritage Agency <ict@onroerenderfgoed.be>
License-File: LICENSE
Keywords: rdf,skos,skosprovider,thesauri,vocabularies
Classifier: Development Status :: 5 - Production/Stable
Classifier: Framework :: Pyramid
Classifier: Programming Language :: Python
Classifier: Programming Language :: Python :: 3.10
Classifier: Programming Language :: Python :: 3.11
Classifier: Programming Language :: Python :: 3.12
Classifier: Programming Language :: Python :: 3.13
Classifier: Topic :: Internet :: WWW/HTTP
Classifier: Topic :: Internet :: WWW/HTTP :: WSGI :: Application
Requires-Python: <3.13.11,>=3.10
Requires-Dist: html5lib==1.1
Requires-Dist: language-tags==1.2.0
Requires-Dist: pyld==2.0.3
Requires-Dist: rfc3987==1.3.8
Provides-Extra: dev
Requires-Dist: black>=25.1.0; extra == 'dev'
Requires-Dist: flake8-bugbear>=24.12.12; extra == 'dev'
Requires-Dist: flake8-import-order>=0.18.2; extra == 'dev'
Requires-Dist: flake8>=7.1.2; extra == 'dev'
Requires-Dist: pre-commit>=4.1.0; extra == 'dev'
Requires-Dist: pytest-cov==6.2.1; extra == 'dev'
Requires-Dist: pytest==8.3.5; extra == 'dev'
Requires-Dist: sphinx-rtd-theme==3.0.2; extra == 'dev'
Requires-Dist: sphinx==8.1.3; extra == 'dev'
